{
    "id": "event_start",
    "prechoice_id": "",
    "text": "У вас на балансе всего 10 рублей! Срочно пополните его прямо сейчас, (кнопка \"пополнить\") а затем закройте это окно.",
    "buttons":
    [
        {
            "text":"Все, пополнил, закрыть",
            "balance":"0",
            "msg":"",
            "choice_id":""
        },
        {
            "text":"Да да.. закрыть",
            "balance":"0",
            "msg":"",
            "choice_id":""
        }
    ]
}